SMART_MRS/IO.py
SMART_MRS/__init__.py
SMART_MRS/applied.py
SMART_MRS/artifacts.py
SMART_MRS/support.py
smart_mrs-2.1.dist-info/METADATA
smart_mrs-2.1.dist-info/WHEEL
smart_mrs-2.1.dist-info/top_level.txt
smart_mrs-2.1.dist-info/RECORD
