Metadata-Version: 2.4
Name: SMART_MRS
Version: 2.1
Summary: Simulated Artifacts for edited Magnetic Resonance Spectroscopy (MRS) data
Author: Hanna Bugler, Amirmohammad Shamaei,Roberto Souza, Ashley D. Harris
Author-email: hanna.bugler@ucalgary.ca
License: MIT
Project-URL: Preprint, https://www.biorxiv.org/content/10.1101/2024.09.19.612894v1
Project-URL: GitHub, https://github.com/HarrisBrainLab/SMART_MRS
Keywords: Magnetic Resonance Spectroscopy,Spectral Simulation,Artifact Simulation
Classifier: Development Status :: 3 - Alpha
Classifier: Intended Audience :: Science/Research
Classifier: License :: OSI Approved :: MIT License
Classifier: Programming Language :: Python :: 3.11
Classifier: Topic :: Scientific/Engineering
Classifier: Topic :: Scientific/Engineering :: Medical Science Apps.
Classifier: Topic :: Software Development :: Libraries :: Python Modules
Requires-Python: >=3.11
Requires-Dist: Nibabel>=5.2.1
Requires-Dist: NumPy>=1.25.2
Requires-Dist: SciPy>=1.11.4
